dimtown/__init__.py
dimtown/spider.py
dimtown_spider-0.1.2.dist-info/METADATA
dimtown_spider-0.1.2.dist-info/WHEEL
dimtown_spider-0.1.2.dist-info/entry_points.txt
dimtown_spider-0.1.2.dist-info/licenses/LICENSE
dimtown_spider-0.1.2.dist-info/RECORD
