Metadata-Version: 2.1
Name: dimtown-spider
Version: 0.1.2
Summary: A spider
Author-Email: Cvandia <106718176+Cvandia@users.noreply.github.com>
License: Apache License 2.0
Requires-Python: <4.0,>=3.9
Requires-Dist: httpx>=0.27.2
Requires-Dist: bs4>=0.0.2
